clean_business_chart/__init__.py
clean_business_chart/barchartwithwaterfall.py
clean_business_chart/clean_business_chart.py
clean_business_chart/columnchartwithwaterfall.py
clean_business_chart/deltachart.py
clean_business_chart/exceptions.py
clean_business_chart/general_functions.py
clean_business_chart/multiplier.py
clean_business_chart-0.2.20.dist-info/AUTHORS.rst
clean_business_chart-0.2.20.dist-info/LICENSE
clean_business_chart-0.2.20.dist-info/METADATA
clean_business_chart-0.2.20.dist-info/WHEEL
clean_business_chart-0.2.20.dist-info/top_level.txt
clean_business_chart-0.2.20.dist-info/RECORD
