Metadata-Version: 2.1
Name: clean-business-chart
Version: 0.2.20
Summary: Clean Business Chart is a Python package for IBCS-like charts based on matplotlib. Currently a column chart with waterfall and a barchart with waterfall are supported.
Home-page: https://github.com/marcelw1323/clean_business_chart
Author: Marcel Wuijtenburg
Author-email: marcelw1323@gmail.com
License: MIT license
Keywords: clean business chart,IBCS,business chart,clean business charts,business charts,chart,charts
Classifier: Development Status :: 4 - Beta
Classifier: Intended Audience :: Developers
Classifier: Intended Audience :: Financial and Insurance Industry
Classifier: License :: OSI Approved :: MIT License
Classifier: Natural Language :: English
Classifier: Programming Language :: Python :: 3
Classifier: Programming Language :: Python :: 3.6
Classifier: Programming Language :: Python :: 3.7
Classifier: Programming Language :: Python :: 3.8
Classifier: Programming Language :: Python :: 3.9
Classifier: Programming Language :: Python :: 3.10
Classifier: Programming Language :: Python :: 3.11
Classifier: Programming Language :: Python :: 3.12
Classifier: Programming Language :: Python :: 3.13
Classifier: Topic :: Scientific/Engineering :: Visualization
Requires-Python: >=3.6
License-File: LICENSE
License-File: AUTHORS.rst
Requires-Dist: matplotlib (>=3.5.1)
Requires-Dist: pandas (>=1.3)
